CHANGES.rst
LICENSE
MANIFEST.in
NOTICE
README.rst
setup.py
doc/Makefile
doc/api.rst
doc/changes.rst
doc/conf.py
doc/configuration.rst
doc/costs.rst
doc/index.rst
doc/installation.rst
doc/license.rst
doc/make.bat
doc/overview.rst
doc/plugins.rst
doc/reports.rst
doc/servicesandusages.rst
doc/statements.rst
doc/tutorial.rst
doc/images/base_usages.png
doc/images/collects_data.png
doc/images/collects_data_plugins.png
doc/images/costs.png
doc/images/mainidea.png
doc/images/push_api.png
doc/images/report_plugins.png
doc/images/service_usages.png
doc/images/services.png
doc/images/services_and_usages.png
doc/images/usages.png
doc/theme/bs/layout.html
doc/theme/bs/theme.conf
doc/theme/bs/static/bs.css
doc/theme/bs/static/jquery.js
doc/theme/bs/static/restyle.js
doc/theme/bs/static/bootstrap/css/bootstrap-responsive.css
doc/theme/bs/static/bootstrap/css/bootstrap-responsive.min.css
doc/theme/bs/static/bootstrap/css/bootstrap.css
doc/theme/bs/static/bootstrap/css/bootstrap.min.css
doc/theme/bs/static/bootstrap/img/glyphicons-halflings-white.png
doc/theme/bs/static/bootstrap/img/glyphicons-halflings.png
doc/theme/bs/static/bootstrap/js/bootstrap.js
doc/theme/bs/static/bootstrap/js/bootstrap.min.js
src/ralph_scrooge/__init__.py
src/ralph_scrooge/admin.py
src/ralph_scrooge/api.py
src/ralph_scrooge/app.py
src/ralph_scrooge/forms.py
src/ralph_scrooge/logging.py
src/ralph_scrooge/menu.py
src/ralph_scrooge/settings-test-scrooge.py
src/ralph_scrooge/settings.py
src/ralph_scrooge/sidebar_menus.py
src/ralph_scrooge/urls.py
src/ralph_scrooge.egg-info/PKG-INFO
src/ralph_scrooge.egg-info/SOURCES.txt
src/ralph_scrooge.egg-info/dependency_links.txt
src/ralph_scrooge.egg-info/entry_points.txt
src/ralph_scrooge.egg-info/not-zip-safe
src/ralph_scrooge.egg-info/pbr.json
src/ralph_scrooge.egg-info/requires.txt
src/ralph_scrooge.egg-info/top_level.txt
src/ralph_scrooge/fixtures/initial_data.yaml
src/ralph_scrooge/management/__init__.py
src/ralph_scrooge/management/commands/__init__.py
src/ralph_scrooge/management/commands/_scrooge_base.py
src/ralph_scrooge/management/commands/scrooge_asset_models.py
src/ralph_scrooge/management/commands/scrooge_assets_with_devices.py
src/ralph_scrooge/management/commands/scrooge_statistics.py
src/ralph_scrooge/management/commands/scrooge_sync.py
